unsuper.py
unsuper-2.2.0.dist-info/licenses/LICENSE
unsuper-2.2.0.dist-info/METADATA
unsuper-2.2.0.dist-info/WHEEL
unsuper-2.2.0.dist-info/entry_points.txt
unsuper-2.2.0.dist-info/top_level.txt
unsuper-2.2.0.dist-info/RECORD
