Metadata-Version: 2.4
Name: unsuper
Version: 2.2.0
Summary: The fastest Android super.img dumper, made in Python.
Author-email: fl0w <flow_dev@protonmail.com>
License: MIT
Project-URL: Homepage, https://github.com/codefl0w/unsuper
Project-URL: Repository, https://github.com/codefl0w/unsuper
Project-URL: Issues, https://github.com/codefl0w/unsuper/issues
Project-URL: Donate, https://coff.ee/fl0w
Requires-Python: >=3.6
License-File: LICENSE
Dynamic: license-file
